tardigrad/__init__.py
tardigrad/layers.py
tardigrad/optim.py
tardigrad/tensor.py
tardigrad/value.py
tardigrad-0.1.0.dist-info/licenses/LICENSE
tardigrad-0.1.0.dist-info/METADATA
tardigrad-0.1.0.dist-info/WHEEL
tardigrad-0.1.0.dist-info/top_level.txt
tardigrad-0.1.0.dist-info/RECORD
